rps_milea/__init__.py
rps_milea/apps.py
rps_milea/settings.py
rps_milea/utils.py
rps_milea/__pycache__/__init__.cpython-311.pyc
rps_milea/__pycache__/apps.cpython-311.pyc
rps_milea/__pycache__/settings.cpython-311.pyc
rps_milea/__pycache__/utils.cpython-311.pyc
rps_milea/admin/__init__.py
rps_milea/admin/choices.py
rps_milea/admin/defaults.py
rps_milea/admin/users.py
rps_milea/admin/__pycache__/__init__.cpython-311.pyc
rps_milea/admin/__pycache__/choices.cpython-311.pyc
rps_milea/admin/__pycache__/defaults.cpython-311.pyc
rps_milea/admin/__pycache__/users.cpython-311.pyc
rps_milea/locale/de/LC_MESSAGES/django.mo
rps_milea/locale/de/LC_MESSAGES/django.po
rps_milea/migrations/0001_initial.py
rps_milea/migrations/0002_alter_mileachoices_created_by_and_more.py
rps_milea/migrations/0003_alter_mileachoices_options_and_more.py
rps_milea/migrations/0004_alter_mileachoices_model.py
rps_milea/migrations/0005_alter_mileachoices_created_by_and_more.py
rps_milea/migrations/__init__.py
rps_milea/migrations/__pycache__/0001_initial.cpython-311.pyc
rps_milea/migrations/__pycache__/0002_alter_mileachoices_created_by_and_more.cpython-311.pyc
rps_milea/migrations/__pycache__/0003_alter_mileachoices_options_and_more.cpython-311.pyc
rps_milea/migrations/__pycache__/0004_alter_mileachoices_model.cpython-311.pyc
rps_milea/migrations/__pycache__/0005_alter_mileachoices_created_by_and_more.cpython-311.pyc
rps_milea/migrations/__pycache__/__init__.cpython-311.pyc
rps_milea/models/__init__.py
rps_milea/models/choices.py
rps_milea/models/defaults.py
rps_milea/models/__pycache__/__init__.cpython-311.pyc
rps_milea/models/__pycache__/choices.cpython-311.pyc
rps_milea/models/__pycache__/defaults.cpython-311.pyc
rps_milea/static/admin/img/icon-calendar.svg
rps_milea/static/admin/img/icon-clock.svg
rps_milea/static/admin/js/SelectFilter2.js
rps_milea/static/admin/js/change_form.js
rps_milea/static/admin/js/admin/RelatedObjectLookups.js
rps_milea/static/milea/css/custom.css
rps_milea_framework-0.0.16.dist-info/METADATA
rps_milea_framework-0.0.16.dist-info/WHEEL
rps_milea_framework-0.0.16.dist-info/top_level.txt
rps_milea_framework-0.0.16.dist-info/RECORD
