Metadata-Version: 2.1
Name: rps-milea-framework
Version: 0.0.16
Summary: Django rps.Milea Framework
Home-page: https://github.com/red-pepper-services/rps-milea-framework
Author: red-pepper-services
Author-email: pypi@schiegg.at
License: MIT
Classifier: Development Status :: 3 - Alpha
Classifier: Framework :: Django
Classifier: Intended Audience :: Developers
Classifier: License :: OSI Approved :: MIT License
Classifier: Operating System :: OS Independent
Classifier: Programming Language :: Python
Requires-Dist: Django >=4.1
Requires-Dist: django-admin-sortable2 >=2.1.4
Requires-Dist: django-object-actions >=4.1.0
Requires-Dist: django-currentuser >=0.6.1
